{
  "hash": "5d9323f4df2a2e3697c94157185614fb",
  "result": {
    "engine": "jupyter",
    "markdown": "---\ntitle: \"hw2\"\nauthor: \"송현주\"\ndate: \"2024-07-17\"\ncategories: [bigdata]\njupyter: python3\n---\n\n\n## 1. 144p mpg 데이터를 이용해 분석 문제를 해결해 보세요.\n\n## Q1 자동차 배기량에 따라 고속도로 연비가 다른지 알아보려고 한다. displ이 4이하인 자동차와 5이상인 자동차 중 어떤 자동차의 hwy 평균이 더 높은지 알아보세요\n\n::: {#a50d5deb .cell execution_count=1}\n``` {.python .cell-code}\nimport numpy as np\nimport pandas as pd\n\ndf = pd.read_csv(\"C:/Users/USER/Documents/LS빅데이터스쿨/MyWeb/data/mpg.csv\")\ntop_displ = df.query('displ >= 5')\nlow_displ = df.query('displ <= 4')\ntop_displ['hwy'].mean()\nlow_displ['hwy'].mean()\n# displ <= 4인 차량이  hwy가 높다\n```\n\n::: {.cell-output .cell-output-display execution_count=1}\n```\n25.96319018404908\n```\n:::\n:::\n\n\n## Q2 자동차 제조 회사에 따라 도시 연비가 어떻게 다른지 알아보려고 합니다. audi와 toyota 중 어느 manufacturer의 cty 평균이 높은지 알아보세요.\n\n::: {#1577a0f6 .cell execution_count=2}\n``` {.python .cell-code}\naudi = df.query('manufacturer == \"audi\"')\ntoyota = df.query('manufacturer== \"toyota\"')\naudi['cty'].mean()\ntoyota['cty'].mean()\n# cty는 toyota가 높다\n```\n\n::: {.cell-output .cell-output-display execution_count=2}\n```\n18.529411764705884\n```\n:::\n:::\n\n\n## Q3 chevrolet, fold, honda 자동차의 고속도로 연비 평균을 알아보려 합니다. 세 회사의 데이터를 추출한 다음 hwy 전체 평균을 구해보세요.\n\n::: {#b0e23bc1 .cell execution_count=3}\n``` {.python .cell-code}\nmpg_new = df.query('manufacturer in [\"chevrolet\", \"old\",\"honda\"]')\nmpg_new['hwy'].mean()\n```\n\n::: {.cell-output .cell-output-display execution_count=3}\n```\n25.321428571428573\n```\n:::\n:::\n\n\n## 2. 153p Q1 audi에서 생산한 자동차 중에 어떤 자동차 모델의 hwy가 높은지 알아보려고 합니다. audi 에서 생산한 자동차 중 hwy가 1\\~5위에 해당하는 자동차를 출력하세요.\n\n::: {#dab6a399 .cell execution_count=4}\n``` {.python .cell-code}\naudi = df.query('manufacturer == \"audi\"')\naudi.sort_values('hwy', ascending = False).head()\n```\n\n::: {.cell-output .cell-output-display execution_count=4}\n```{=html}\n<div>\n<style scoped>\n    .dataframe tbody tr th:only-of-type {\n        vertical-align: middle;\n    }\n\n    .dataframe tbody tr th {\n        vertical-align: top;\n    }\n\n    .dataframe thead th {\n        text-align: right;\n    }\n</style>\n<table border=\"1\" class=\"dataframe\">\n  <thead>\n    <tr style=\"text-align: right;\">\n      <th></th>\n      <th>manufacturer</th>\n      <th>model</th>\n      <th>displ</th>\n      <th>year</th>\n      <th>cyl</th>\n      <th>trans</th>\n      <th>drv</th>\n      <th>cty</th>\n      <th>hwy</th>\n      <th>fl</th>\n      <th>category</th>\n    </tr>\n  </thead>\n  <tbody>\n    <tr>\n      <th>2</th>\n      <td>audi</td>\n      <td>a4</td>\n      <td>2.0</td>\n      <td>2008</td>\n      <td>4</td>\n      <td>manual(m6)</td>\n      <td>f</td>\n      <td>20</td>\n      <td>31</td>\n      <td>p</td>\n      <td>compact</td>\n    </tr>\n    <tr>\n      <th>3</th>\n      <td>audi</td>\n      <td>a4</td>\n      <td>2.0</td>\n      <td>2008</td>\n      <td>4</td>\n      <td>auto(av)</td>\n      <td>f</td>\n      <td>21</td>\n      <td>30</td>\n      <td>p</td>\n      <td>compact</td>\n    </tr>\n    <tr>\n      <th>0</th>\n      <td>audi</td>\n      <td>a4</td>\n      <td>1.8</td>\n      <td>1999</td>\n      <td>4</td>\n      <td>auto(l5)</td>\n      <td>f</td>\n      <td>18</td>\n      <td>29</td>\n      <td>p</td>\n      <td>compact</td>\n    </tr>\n    <tr>\n      <th>1</th>\n      <td>audi</td>\n      <td>a4</td>\n      <td>1.8</td>\n      <td>1999</td>\n      <td>4</td>\n      <td>manual(m5)</td>\n      <td>f</td>\n      <td>21</td>\n      <td>29</td>\n      <td>p</td>\n      <td>compact</td>\n    </tr>\n    <tr>\n      <th>9</th>\n      <td>audi</td>\n      <td>a4 quattro</td>\n      <td>2.0</td>\n      <td>2008</td>\n      <td>4</td>\n      <td>manual(m6)</td>\n      <td>4</td>\n      <td>20</td>\n      <td>28</td>\n      <td>p</td>\n      <td>compact</td>\n    </tr>\n  </tbody>\n</table>\n</div>\n```\n:::\n:::\n\n\n",
    "supporting": [
      "hw2_files"
    ],
    "filters": [],
    "includes": {
      "include-in-header": [
        "<script src=\"https://cdnjs.cloudflare.com/ajax/libs/require.js/2.3.6/require.min.js\" integrity=\"sha512-c3Nl8+7g4LMSTdrm621y7kf9v3SDPnhxLNhcjFJbKECVnmZHTdo+IRO05sNLTH/D3vA6u1X32ehoLC7WFVdheg==\" crossorigin=\"anonymous\"></script>\n<script src=\"https://cdnjs.cloudflare.com/ajax/libs/jquery/3.5.1/jquery.min.js\" integrity=\"sha512-bLT0Qm9VnAYZDflyKcBaQ2gg0hSYNQrJ8RilYldYQ1FxQYoCLtUjuuRuZo+fjqhx/qtq/1itJ0C2ejDxltZVFg==\" crossorigin=\"anonymous\" data-relocate-top=\"true\"></script>\n<script type=\"application/javascript\">define('jquery', [],function() {return window.jQuery;})</script>\n"
      ]
    }
  }
}